zope.annotation-5.2-py3.12-nspkg.pth
zope/annotation/__init__.py
zope/annotation/attribute.py
zope/annotation/configure.zcml
zope/annotation/factory.py
zope/annotation/interfaces.py
zope/annotation/tests/__init__.py
zope/annotation/tests/annotations.py
zope/annotation/tests/test_attributeannotations.py
zope/annotation/tests/test_configure.py
zope/annotation/tests/test_factory.py
zope_annotation-5.2.dist-info/licenses/LICENSE.txt
zope_annotation-5.2.dist-info/METADATA
zope_annotation-5.2.dist-info/WHEEL
zope_annotation-5.2.dist-info/namespace_packages.txt
zope_annotation-5.2.dist-info/top_level.txt
zope_annotation-5.2.dist-info/RECORD
