Metadata-Version: 2.4
Name: zope.annotation
Version: 5.2
Summary: Object annotation mechanism
Home-page: https://github.com/zopefoundation/zope.annotation
Author: Zope Foundation and Contributors
Author-email: zope-dev@zope.dev
License: ZPL-2.1
Keywords: zope annotation ZODB zope3 ztk
Classifier: Development Status :: 5 - Production/Stable
Classifier: Intended Audience :: Developers
Classifier: License :: OSI Approved :: Zope Public License
Classifier: Programming Language :: Python
Classifier: Programming Language :: Python :: 3
Classifier: Programming Language :: Python :: 3.9
Classifier: Programming Language :: Python :: 3.10
Classifier: Programming Language :: Python :: 3.11
Classifier: Programming Language :: Python :: 3.12
Classifier: Programming Language :: Python :: 3.13
Classifier: Programming Language :: Python :: Implementation :: CPython
Classifier: Programming Language :: Python :: Implementation :: PyPy
Classifier: Natural Language :: English
Classifier: Operating System :: OS Independent
Classifier: Topic :: Internet :: WWW/HTTP
Classifier: Topic :: Software Development
Requires-Python: >=3.9
License-File: LICENSE.txt
Requires-Dist: setuptools
Requires-Dist: zope.interface
Requires-Dist: zope.component
Requires-Dist: zope.location
Requires-Dist: zope.proxy
Provides-Extra: btrees
Requires-Dist: BTrees; extra == "btrees"
Requires-Dist: persistent; extra == "btrees"
Provides-Extra: docs
Requires-Dist: Sphinx; extra == "docs"
Requires-Dist: repoze.sphinx.autointerface; extra == "docs"
Requires-Dist: zope.component[zcml]; extra == "docs"
Requires-Dist: zope.configuration; extra == "docs"
Requires-Dist: zope.testing; extra == "docs"
Requires-Dist: zope.testrunner; extra == "docs"
Provides-Extra: test
Requires-Dist: zope.component[zcml]; extra == "test"
Requires-Dist: zope.configuration; extra == "test"
Requires-Dist: zope.testing; extra == "test"
Requires-Dist: zope.testrunner; extra == "test"
Provides-Extra: testing
Requires-Dist: zope.component[zcml]; extra == "testing"
Requires-Dist: zope.configuration; extra == "testing"
Requires-Dist: zope.testing; extra == "testing"
Requires-Dist: zope.testrunner; extra == "testing"
Requires-Dist: nose; extra == "testing"
Requires-Dist: coverage; extra == "testing"
Provides-Extra: zcml
Requires-Dist: zope.component[zcml]; extra == "zcml"
Requires-Dist: zope.configuration; extra == "zcml"
Dynamic: author
Dynamic: author-email
Dynamic: classifier
Dynamic: description
Dynamic: home-page
Dynamic: keywords
Dynamic: license
Dynamic: license-file
Dynamic: provides-extra
Dynamic: requires-dist
Dynamic: requires-python
Dynamic: summary
